{
  "attributes": {
    "minecraft:audio/ambient_sounds": {
      "additions": {
        "sound": "minecraft:ambient.crimson_forest.additions",
        "tick_chance": 0.0033
      },
      "loop": {
        "sound_id": "stellarity:ambient.dark"
      },
      "mood": {
        "block_search_extent": 3,
        "offset": 2.0,
        "sound": "minecraft:ambient.basalt_deltas.mood",
        "tick_delay": 1250
      }
    },
    "minecraft:visual/ambient_light_color": "#3f473f",
    "minecraft:visual/ambient_particles": [
      {
        "particle": {
          "type": "minecraft:white_ash"
        },
        "probability": 0.01
      }
    ],
    "minecraft:visual/fog_color": "#000000",
    "minecraft:visual/sky_color": "#000000",
    "minecraft:visual/water_fog_color": "#c4c4cf"
  },
  "carvers": [],
  "downfall": 0.9,
  "effects": {
    "foliage_color": "#c2c2c2",
    "grass_color": "#dedede",
    "water_color": "#e5eeff"
  },
  "features": [
    [
      "stellarity:global/stalactites"
    ],
    [],
    [],
    [
      "stellarity:ashfall_deltas/water_deltas",
      "stellarity:ashfall_deltas/grass_deltas",
      "stellarity:ashfall_deltas/basalt_columns"
    ]
  ],
  "has_precipitation": false,
  "spawn_costs": {},
  "spawners": {
    "ambient": [],
    "axolotls": [],
    "creature": [],
    "misc": [],
    "monster": [],
    "underground_water_creature": [],
    "water_ambient": [],
    "water_creature": []
  },
  "temperature": 0.8
}